julesTk/__init__.py
julesTk/app.py
julesTk/controller/__init__.py
julesTk/controller/poller.py
julesTk/controller/viewset.py
julesTk/controller/window.py
julesTk/model/__init__.py
julesTk/model/random.py
julesTk/utils/__init__.py
julesTk/utils/console.py
julesTk/utils/font.py
julesTk/utils/modals.py
julesTk/utils/observe.py
julesTk/utils/progress.py
julesTk/view/__init__.py
julesTk/view/plot.py
julesTk/view/viewset.py
julesTk/view/window.py
julesTk-0.3.3.dist-info/DESCRIPTION.rst
julesTk-0.3.3.dist-info/METADATA
julesTk-0.3.3.dist-info/RECORD
julesTk-0.3.3.dist-info/WHEEL
julesTk-0.3.3.dist-info/entry_points.txt
julesTk-0.3.3.dist-info/metadata.json
julesTk-0.3.3.dist-info/top_level.txt
