Metadata-Version: 2.0
Name: julesTk
Version: 0.3.3
Summary: MVC Framework for TKinter
Home-page: https://github.com/jjongbloets/julesTk
Author: Joeri Jongbloets
Author-email: joeri@jongbloets.net
License: MIT
Keywords: tkinter mvc
Platform: UNKNOWN
Classifier: Development Status :: 3 - Alpha
Classifier: Intended Audience :: Developers
Classifier: License :: OSI Approved :: MIT License
Classifier: Programming Language :: Python :: 2.7
Classifier: Programming Language :: Python :: 3
Classifier: Programming Language :: Python :: 3.3
Classifier: Programming Language :: Python :: 3.4
Classifier: Programming Language :: Python :: 3.5
Provides-Extra: plot
Requires-Dist: matplotlib; extra == 'plot'
